<?xml version="1.0" encoding="UTF-8"?>

<Music creationTime="12 Dec 2021 11:07:06" lastModifiedTime="1 Jan 1970 8:00:00">
  <TempoTrack>
    <Tempo startBeat="0.0" bpm="60.0"/>
    <Tempo startBeat="48.0" bpm="30.0"/>
    <Tempo startBeat="52.0" bpm="60.0"/>
    <Tempo startBeat="84.0" bpm="30.0"/>
    <Tempo startBeat="89.0" bpm="54.00000540000054"/>
    <Tempo startBeat="117.0" bpm="20.0"/>
    <Tempo startBeat="121.0" bpm="54.00000540000054"/>
    <TimeSig startBeat="0.0" sigBeat="4" sigBeatsType="4"/>
    <TimeSig startBeat="48.0" sigBeat="9" sigBeatsType="8"/>
    <TimeSig startBeat="53.0" sigBeat="4" sigBeatsType="4"/>
    <TimeSig startBeat="84.0" sigBeat="9" sigBeatsType="8"/>
    <TimeSig startBeat="89.0" sigBeat="4" sigBeatsType="4"/>
    <TimeSig startBeat="117.0" sigBeat="17" sigBeatsType="16"/>
    <TimeSig startBeat="122.0" sigBeat="4" sigBeatsType="4"/>
  </TempoTrack>
  <PitchTrack>
    <Pitch startBeat="0.0" pitch="60"/>
  </PitchTrack>
  <MarkerTrack id="1015" name="&#26631;&#35760;"/>
  <ChordTrack name="&#26609;&#24335;&#21644;&#24358;&#36827;&#34892;" id="1069"/>
  <MidiTrack id="1020" name="Cantus">
    <MidiBlock name="Cantus" length="164.2777714133433" id="1079" startBeat="0.0">
      <Note pitch="66" beat="15.5" length="0.5" velocity="55"/>
      <Note pitch="71" beat="16.0" length="1.0" velocity="68"/>
      <Note pitch="71" beat="17.0" length="0.5" velocity="62"/>
      <Note pitch="71" beat="17.5" length="0.5" velocity="62"/>
      <Note pitch="70" beat="18.0" length="1.0" velocity="58"/>
      <Note pitch="71" beat="19.0" length="0.5" velocity="63"/>
      <Note pitch="73" beat="19.5" length="0.5" velocity="63"/>
      <Note pitch="73" beat="20.0" length="2.0" velocity="61"/>
      <Note pitch="66" beat="22.0" length="1.0" velocity="52"/>
      <Note pitch="66" beat="23.0" length="1.0" velocity="59"/>
      <Note pitch="71" beat="24.0" length="1.5" velocity="71"/>
      <Note pitch="71" beat="25.5" length="0.5" velocity="62"/>
      <Note pitch="71" beat="26.0" length="0.5083333333333329" velocity="60"/>
      <Note pitch="70" beat="26.5" length="0.5083333333333329" velocity="60"/>
      <Note pitch="71" beat="27.0" length="0.7114583333333329" velocity="65"/>
      <Note pitch="73" beat="27.75" length="0.25" velocity="65"/>
      <Note pitch="73" beat="28.0" length="3.0" velocity="60"/>
      <Note pitch="66" beat="31.0" length="1.0" velocity="46"/>
      <Note pitch="75" beat="32.0" length="1.5" velocity="73"/>
      <Note pitch="75" beat="33.5" length="0.5" velocity="66"/>
      <Note pitch="75" beat="34.0" length="1.0" velocity="60"/>
      <Note pitch="70" beat="35.0" length="1.0" velocity="56"/>
      <Note pitch="73" beat="36.0" length="2.0" velocity="60"/>
      <Note pitch="71" beat="38.0" length="1.0" velocity="57"/>
      <Note pitch="70" beat="39.0" length="1.0" velocity="57"/>
      <Note pitch="68" beat="40.0" length="0.6760416666666629" velocity="51"/>
      <Note pitch="71" beat="40.66458333333333" length="0.6791666666666671"
            velocity="67"/>
      <Note pitch="75" beat="41.33229166666666" length="0.6322916666666671"
            velocity="70"/>
      <Note pitch="80" beat="42.0" length="1.5" velocity="69"/>
      <Note pitch="78" beat="43.5" length="0.5" velocity="55"/>
      <Note pitch="76" beat="44.0" length="2.0" velocity="61"/>
      <Note pitch="66" beat="52.0" length="0.5" velocity="75"/>
      <Note pitch="71" beat="52.5" length="1.0" velocity="100"/>
      <Note pitch="71" beat="53.5" length="0.5" velocity="82"/>
      <Note pitch="71" beat="54.0" length="0.5" velocity="85"/>
      <Note pitch="70" beat="54.5" length="1.0" velocity="80"/>
      <Note pitch="71" beat="55.5" length="0.5" velocity="87"/>
      <Note pitch="73" beat="56.0" length="0.5" velocity="93"/>
      <Note pitch="73" beat="56.5" length="2.0" velocity="87"/>
      <Note pitch="66" beat="58.5" length="1.0" velocity="68"/>
      <Note pitch="66" beat="59.5" length="1.0" velocity="85"/>
      <Note pitch="71" beat="60.5" length="1.0" velocity="94"/>
      <Note pitch="71" beat="61.5" length="0.5" velocity="92"/>
      <Note pitch="71" beat="62.0" length="0.5" velocity="84"/>
      <Note pitch="71" beat="62.5" length="0.5083333333333329" velocity="86"/>
      <Note pitch="70" beat="63.0" length="0.4729166666666629" velocity="83"/>
      <Note pitch="71" beat="63.5" length="0.75" velocity="85"/>
      <Note pitch="73" beat="64.25" length="0.25" velocity="91"/>
      <Note pitch="73" beat="64.5" length="3.0" velocity="83"/>
      <Note pitch="66" beat="67.5" length="1.0" velocity="49"/>
      <Note pitch="75" beat="68.5" length="1.0" velocity="74"/>
      <Note pitch="75" beat="69.5" length="0.5" velocity="63"/>
      <Note pitch="75" beat="70.0" length="0.5" velocity="58"/>
      <Note pitch="75" beat="70.5" length="1.5" velocity="56"/>
      <Note pitch="70" beat="72.0" length="0.5" velocity="58"/>
      <Note pitch="73" beat="72.5" length="2.0" velocity="63"/>
      <Note pitch="71" beat="74.5" length="1.0" velocity="54"/>
      <Note pitch="70" beat="75.5" length="1.0" velocity="54"/>
      <Note pitch="68" beat="76.5" length="0.6760416666666629" velocity="54"/>
      <Note pitch="71" beat="77.16458333333333" length="0.6791666666666742"
            velocity="69"/>
      <Note pitch="75" beat="77.83229166666666" length="0.6322916666666742"
            velocity="68"/>
      <Note pitch="80" beat="78.5" length="0.6645833333333258" velocity="68"/>
      <Note pitch="80" beat="79.16458333333333" length="0.6677083333333371"
            velocity="67"/>
      <Note pitch="78" beat="79.83229166666666" length="0.6677083333333371"
            velocity="58"/>
      <Note pitch="76" beat="80.5" length="2.0" velocity="57"/>
      <Note pitch="71" beat="88.0" length="1.0" velocity="60"/>
      <Note pitch="71" beat="89.0" length="0.6645833333333258" velocity="58"/>
      <Note pitch="71" beat="89.66458333333333" length="0.6677083333333371"
            velocity="64"/>
      <Note pitch="71" beat="90.33229166666666" length="0.6677083333333371"
            velocity="58"/>
      <Note pitch="71" beat="91.0" length="0.6645833333333258" velocity="61"/>
      <Note pitch="71" beat="91.66458333333333" length="0.6677083333333371"
            velocity="61"/>
      <Note pitch="71" beat="92.33229166666666" length="0.6677083333333371"
            velocity="60"/>
      <Note pitch="74" beat="93.0" length="2.0" velocity="67"/>
      <Note pitch="71" beat="95.0" length="1.0" velocity="60"/>
      <Note pitch="69" beat="96.0" length="1.0" velocity="55"/>
      <Note pitch="69" beat="97.0" length="1.0" velocity="60"/>
      <Note pitch="69" beat="98.0" length="1.0" velocity="60"/>
      <Note pitch="69" beat="99.0" length="0.6760416666666629" velocity="64"/>
      <Note pitch="71" beat="99.66458333333333" length="0.6322916666666742"
            velocity="66"/>
      <Note pitch="72" beat="100.3322916666667" length="0.6677083333333371"
            velocity="63"/>
      <Note pitch="71" beat="101.0" length="2.0" velocity="56"/>
      <Note pitch="71" beat="104.0" length="1.0" velocity="54"/>
      <Note pitch="71" beat="105.0" length="0.6645833333333258" velocity="55"/>
      <Note pitch="71" beat="105.6645833333333" length="0.6677083333333371"
            velocity="59"/>
      <Note pitch="71" beat="106.3322916666667" length="0.6677083333333371"
            velocity="61"/>
      <Note pitch="71" beat="107.0" length="0.6645833333333258" velocity="62"/>
      <Note pitch="71" beat="107.6645833333333" length="0.6677083333333371"
            velocity="56"/>
      <Note pitch="71" beat="108.3322916666667" length="0.6677083333333371"
            velocity="60"/>
      <Note pitch="74" beat="109.0" length="2.0" velocity="63"/>
      <Note pitch="71" beat="111.0" length="1.0" velocity="62"/>
      <Note pitch="69" beat="112.0" length="1.0" velocity="56"/>
      <Note pitch="69" beat="113.0" length="1.0" velocity="60"/>
      <Note pitch="69" beat="114.0" length="1.0" velocity="58"/>
      <Note pitch="69" beat="115.0" length="0.6760416666666629" velocity="62"/>
      <Note pitch="71" beat="115.6645833333333" length="0.6322916666666742"
            velocity="65"/>
      <Note pitch="72" beat="116.3322916666667" length="0.6677083333333371"
            velocity="64"/>
      <Note pitch="71" beat="117.0" length="3.0" velocity="59"/>
      <Note pitch="66" beat="120.75" length="0.5" velocity="76"/>
      <Note pitch="71" beat="121.25" length="1.0" velocity="94"/>
      <Note pitch="71" beat="122.25" length="0.5" velocity="87"/>
      <Note pitch="71" beat="122.75" length="0.5" velocity="82"/>
      <Note pitch="70" beat="123.25" length="1.019791666666663" velocity="78"/>
      <Note pitch="71" beat="124.25" length="0.4729166666666629" velocity="88"/>
      <Note pitch="73" beat="124.75" length="0.5" velocity="85"/>
      <Note pitch="73" beat="125.25" length="2.0" velocity="86"/>
      <Note pitch="66" beat="127.25" length="1.0" velocity="66"/>
      <Note pitch="66" beat="128.75" length="0.5" velocity="77"/>
      <Note pitch="71" beat="129.25" length="1.5" velocity="95"/>
      <Note pitch="71" beat="130.75" length="0.5" velocity="87"/>
      <Note pitch="71" beat="131.25" length="0.5083333333333258" velocity="85"/>
      <Note pitch="70" beat="131.75" length="0.5083333333333258" velocity="78"/>
      <Note pitch="71" beat="132.25" length="0.7114583333333258" velocity="89"/>
      <Note pitch="73" beat="133.0" length="0.25" velocity="90"/>
      <Note pitch="73" beat="133.25" length="3.0" velocity="86"/>
      <Note pitch="66" beat="136.25" length="1.0" velocity="66"/>
      <Note pitch="75" beat="137.25" length="1.0" velocity="99"/>
      <Note pitch="75" beat="138.25" length="0.5" velocity="90"/>
      <Note pitch="75" beat="138.75" length="0.5" velocity="83"/>
      <Note pitch="75" beat="139.25" length="1.0" velocity="81"/>
      <Note pitch="70" beat="140.25" length="0.5" velocity="77"/>
      <Note pitch="70" beat="140.75" length="0.5" velocity="89"/>
      <Note pitch="73" beat="141.25" length="2.0" velocity="91"/>
      <Note pitch="71" beat="143.25" length="1.0" velocity="81"/>
      <Note pitch="68" beat="145.25" length="1.0" velocity="73"/>
      <Note pitch="68" beat="146.25" length="0.5" velocity="82"/>
      <Note pitch="68" beat="146.75" length="0.5" velocity="81"/>
      <Note pitch="71" beat="147.25" length="1.0" velocity="94"/>
      <Note pitch="70" beat="148.25" length="0.5" velocity="82"/>
      <Note pitch="70" beat="148.75" length="0.5" velocity="83"/>
      <Note pitch="67" beat="149.25" length="2.0" velocity="77"/>
      <Note pitch="66" beat="151.25" length="1.0" velocity="78"/>
      <Note pitch="64" beat="153.25" length="1.0" velocity="75"/>
      <Note pitch="64" beat="154.25" length="0.5" velocity="79"/>
      <Note pitch="64" beat="154.75" length="0.5" velocity="86"/>
      <Note pitch="68" beat="155.25" length="1.0" velocity="91"/>
      <Note pitch="66" beat="156.25" length="0.5" velocity="79"/>
      <Note pitch="66" beat="156.75" length="0.5" velocity="88"/>
      <Note pitch="63" beat="157.25" length="2.0" velocity="77"/>
    </MidiBlock>
  </MidiTrack>
  <MidiTrack id="1082" name="Piano">
    <MidiBlock name="Piano" length="188.4965189914683" id="1099" startBeat="0.0">
      <Note pitch="71" beat="0.0" length="2.0" velocity="70"/>
      <Note pitch="63" beat="0.0" length="2.0" velocity="58"/>
      <Note pitch="66" beat="0.0" length="2.0" velocity="58"/>
      <Note pitch="47" beat="0.0" length="2.039583333333333" velocity="68"/>
      <Note pitch="54" beat="0.0" length="2.0" velocity="68"/>
      <Note pitch="70" beat="2.0" length="0.5083333333333333" velocity="67"/>
      <Note pitch="64" beat="2.0" length="1.898958333333333" velocity="49"/>
      <Note pitch="66" beat="2.0" length="1.898958333333333" velocity="49"/>
      <Note pitch="49" beat="2.0" length="1.898958333333333" velocity="74"/>
      <Note pitch="54" beat="2.0" length="1.898958333333333" velocity="74"/>
      <Note pitch="76" beat="2.5" length="1.019791666666666" velocity="80"/>
      <Note pitch="75" beat="3.5" length="0.4729166666666664" velocity="72"/>
      <Note pitch="75" beat="4.0" length="2.0" velocity="70"/>
      <Note pitch="63" beat="4.0" length="2.0" velocity="39"/>
      <Note pitch="66" beat="4.0" length="2.0" velocity="39"/>
      <Note pitch="71" beat="4.0" length="2.0" velocity="39"/>
      <Note pitch="47" beat="4.0" length="2.039583333333333" velocity="71"/>
      <Note pitch="54" beat="4.0" length="2.0" velocity="71"/>
      <Note pitch="64" beat="6.0" length="0.5083333333333329" velocity="63"/>
      <Note pitch="68" beat="6.0" length="0.5" velocity="63"/>
      <Note pitch="70" beat="6.0" length="0.5083333333333329" velocity="63"/>
      <Note pitch="73" beat="6.0" length="0.5083333333333329" velocity="63"/>
      <Note pitch="49" beat="6.0" length="1.527083333333334" velocity="61"/>
      <Note pitch="54" beat="6.0" length="1.527083333333334" velocity="61"/>
      <Note pitch="68" beat="6.5" length="1.019791666666666" velocity="71"/>
      <Note pitch="80" beat="6.5" length="1.019791666666666" velocity="71"/>
      <Note pitch="67" beat="7.5" length="0.4729166666666664" velocity="69"/>
      <Note pitch="79" beat="7.5" length="0.4729166666666664" velocity="69"/>
      <Note pitch="55" beat="7.5" length="0.4729166666666664" velocity="65"/>
      <Note pitch="66" beat="8.0" length="0.5083333333333329" velocity="49"/>
      <Note pitch="67" beat="8.0" length="1.898958333333333" velocity="51"/>
      <Note pitch="79" beat="8.0" length="1.898958333333333" velocity="51"/>
      <Note pitch="55" beat="8.0" length="0.515625" velocity="73"/>
      <Note pitch="51" beat="8.0" length="1.933333333333334" velocity="55"/>
      <Note pitch="73" beat="8.5" length="1.019791666666666" velocity="85"/>
      <Note pitch="61" beat="8.5" length="1.039583333333333" velocity="90"/>
      <Note pitch="72" beat="9.5" length="0.4729166666666664" velocity="80"/>
      <Note pitch="60" beat="9.5" length="0.4729166666666664" velocity="79"/>
      <Note pitch="72" beat="10.0" length="0.5083333333333329" velocity="84"/>
      <Note pitch="66" beat="10.0" length="0.5" velocity="71"/>
      <Note pitch="78" beat="10.0" length="0.5" velocity="71"/>
      <Note pitch="60" beat="10.0" length="1.933333333333334" velocity="80"/>
      <Note pitch="56" beat="10.0" length="1.933333333333334" velocity="83"/>
      <Note pitch="78" beat="10.5" length="0.5197916666666664" velocity="94"/>
      <Note pitch="66" beat="10.5" length="0.5197916666666664" velocity="98"/>
      <Note pitch="77" beat="11.5" length="0.4729166666666664" velocity="81"/>
      <Note pitch="65" beat="11.5" length="0.4802083333333336" velocity="84"/>
      <Note pitch="71" beat="12.0" length="0.5083333333333329" velocity="74"/>
      <Note pitch="65" beat="12.0" length="2.039583333333333" velocity="63"/>
      <Note pitch="77" beat="12.0" length="2.039583333333333" velocity="63"/>
      <Note pitch="59" beat="12.0" length="0.515625" velocity="77"/>
      <Note pitch="49" beat="12.0" length="2.078125" velocity="65"/>
      <Note pitch="75" beat="12.5" length="1.019791666666666" velocity="95"/>
      <Note pitch="63" beat="12.5" length="1.039583333333333" velocity="91"/>
      <Note pitch="73" beat="13.5" length="0.5" velocity="80"/>
      <Note pitch="61" beat="13.5" length="0.5" velocity="80"/>
      <Note pitch="71" beat="14.0" length="0.5083333333333329" velocity="73"/>
      <Note pitch="64" beat="14.0" length="1.019791666666666" velocity="67"/>
      <Note pitch="73" beat="14.0" length="1.019791666666666" velocity="67"/>
      <Note pitch="76" beat="14.0" length="1.019791666666666" velocity="67"/>
      <Note pitch="59" beat="14.0" length="0.4802083333333336" velocity="82"/>
      <Note pitch="54" beat="14.0" length="1.5" velocity="91"/>
      <Note pitch="61" beat="14.0" length="1.801041666666666" velocity="91"/>
      <Note pitch="70" beat="14.5" length="0.5083333333333329" velocity="77"/>
      <Note pitch="58" beat="14.5" length="0.5083333333333329" velocity="83"/>
      <Note pitch="68" beat="15.0" length="0.5083333333333329" velocity="81"/>
      <Note pitch="56" beat="15.0" length="0.5083333333333329" velocity="76"/>
      <Note pitch="66" beat="15.5" length="0.4729166666666664" velocity="76"/>
      <Note pitch="54" beat="15.5" length="0.3010416666666664" velocity="85"/>
      <Note pitch="63" beat="16.0" length="0.5" velocity="67"/>
      <Note pitch="66" beat="16.0" length="0.5" velocity="67"/>
      <Note pitch="71" beat="16.0" length="0.5" velocity="67"/>
      <Note pitch="47" beat="16.0" length="0.5" velocity="61"/>
      <Note pitch="54" beat="16.0" length="0.5" velocity="61"/>
      <Note pitch="63" beat="17.0" length="0.25" velocity="61"/>
      <Note pitch="66" beat="17.0" length="0.25" velocity="61"/>
      <Note pitch="71" beat="17.0" length="0.25" velocity="61"/>
      <Note pitch="47" beat="17.0" length="0.25" velocity="65"/>
      <Note pitch="54" beat="17.0" length="0.25" velocity="65"/>
      <Note pitch="63" beat="17.5" length="0.234375" velocity="62"/>
      <Note pitch="66" beat="17.5" length="0.234375" velocity="62"/>
      <Note pitch="71" beat="17.5" length="0.234375" velocity="62"/>
      <Note pitch="47" beat="17.5" length="0.234375" velocity="63"/>
      <Note pitch="54" beat="17.5" length="0.234375" velocity="63"/>
      <Note pitch="64" beat="18.0" length="0.5" velocity="57"/>
      <Note pitch="66" beat="18.0" length="0.5" velocity="57"/>
      <Note pitch="70" beat="18.0" length="0.5083333333333329" velocity="57"/>
      <Note pitch="49" beat="18.0" length="0.5083333333333329" velocity="62"/>
      <Note pitch="54" beat="18.0" length="0.5" velocity="62"/>
      <Note pitch="64" beat="19.0" length="0.25" velocity="63"/>
      <Note pitch="66" beat="19.0" length="0.25" velocity="63"/>
      <Note pitch="71" beat="19.0" length="0.2541666666666664" velocity="63"/>
      <Note pitch="47" beat="19.0" length="0.2541666666666664" velocity="60"/>
      <Note pitch="54" beat="19.0" length="0.25" velocity="60"/>
      <Note pitch="64" beat="19.5" length="0.234375" velocity="66"/>
      <Note pitch="66" beat="19.5" length="0.234375" velocity="66"/>
      <Note pitch="73" beat="19.5" length="0.234375" velocity="66"/>
      <Note pitch="46" beat="19.5" length="0.234375" velocity="62"/>
      <Note pitch="54" beat="19.5" length="0.234375" velocity="62"/>
      <Note pitch="64" beat="20.0" length="4.0" velocity="50"/>
      <Note pitch="66" beat="20.0" length="4.0" velocity="50"/>
      <Note pitch="73" beat="20.0" length="4.0" velocity="50"/>
      <Note pitch="46" beat="20.0" length="4.0" velocity="50"/>
      <Note pitch="54" beat="20.0" length="4.0" velocity="50"/>
      <Note pitch="63" beat="24.0" length="0.75" velocity="34"/>
      <Note pitch="66" beat="24.0" length="0.75" velocity="34"/>
      <Note pitch="71" beat="24.0" length="0.75" velocity="34"/>
      <Note pitch="47" beat="24.0" length="0.75" velocity="40"/>
      <Note pitch="54" beat="24.0" length="0.75" velocity="40"/>
      <Note pitch="63" beat="25.5" length="0.234375" velocity="38"/>
      <Note pitch="66" beat="25.5" length="0.234375" velocity="38"/>
      <Note pitch="71" beat="25.5" length="0.234375" velocity="38"/>
      <Note pitch="47" beat="25.5" length="0.234375" velocity="37"/>
      <Note pitch="54" beat="25.5" length="0.234375" velocity="37"/>
      <Note pitch="63" beat="26.0" length="0.2541666666666664" velocity="39"/>
      <Note pitch="66" beat="26.0" length="0.25" velocity="39"/>
      <Note pitch="71" beat="26.0" length="0.2541666666666664" velocity="39"/>
      <Note pitch="47" beat="26.0" length="0.2541666666666664" velocity="37"/>
      <Note pitch="54" beat="26.0" length="0.25" velocity="37"/>
      <Note pitch="64" beat="26.5" length="0.25" velocity="41"/>
      <Note pitch="66" beat="26.5" length="0.25" velocity="41"/>
      <Note pitch="70" beat="26.5" length="0.2541666666666664" velocity="41"/>
      <Note pitch="49" beat="26.5" length="0.2541666666666664" velocity="41"/>
      <Note pitch="54" beat="26.5" length="0.25" velocity="41"/>
      <Note pitch="64" beat="27.0" length="0.3552083333333336" velocity="39"/>
      <Note pitch="66" beat="27.0" length="0.3552083333333336" velocity="39"/>
      <Note pitch="71" beat="27.0" length="0.3552083333333336" velocity="39"/>
      <Note pitch="47" beat="27.0" length="0.3552083333333336" velocity="38"/>
      <Note pitch="54" beat="27.0" length="0.3552083333333336" velocity="38"/>
      <Note pitch="64" beat="27.75" length="0.25" velocity="44"/>
      <Note pitch="66" beat="27.75" length="0.25" velocity="44"/>
      <Note pitch="73" beat="27.75" length="0.25" velocity="44"/>
      <Note pitch="46" beat="27.75" length="0.25" velocity="41"/>
      <Note pitch="54" beat="27.75" length="0.25" velocity="41"/>
      <Note pitch="64" beat="28.0" length="4.078125" velocity="42"/>
      <Note pitch="66" beat="28.0" length="4.078125" velocity="42"/>
      <Note pitch="73" beat="28.0" length="4.078125" velocity="42"/>
      <Note pitch="46" beat="28.0" length="4.0" velocity="39"/>
      <Note pitch="54" beat="28.0" length="4.0" velocity="39"/>
      <Note pitch="75" beat="32.0" length="3.566666666666663" velocity="38"/>
      <Note pitch="63" beat="32.0" length="3.94895833333333" velocity="60"/>
      <Note pitch="54" beat="32.0" length="3.0" velocity="38"/>
      <Note pitch="47" beat="32.0" length="4.0" velocity="62"/>
      <Note pitch="55" beat="35.0" length="1.0" velocity="41"/>
      <Note pitch="70" beat="35.5" length="0.5083333333333329" velocity="30"/>
      <Note pitch="63" beat="35.94895833333333" length="0.05104166666666998"
            velocity="68"/>
      <Note pitch="73" beat="36.0" length="1.93333333333333" velocity="43"/>
      <Note pitch="63" beat="36.0" length="3.60520833333333" velocity="71"/>
      <Note pitch="56" beat="36.0" length="3.0" velocity="40"/>
      <Note pitch="47" beat="36.0" length="4.0" velocity="67"/>
      <Note pitch="71" beat="38.0" length="1.019791666666663" velocity="34"/>
      <Note pitch="70" beat="39.0" length="0.94895833333333" velocity="38"/>
      <Note pitch="58" beat="39.0" length="1.0" velocity="45"/>
      <Note pitch="63" beat="39.94895833333333" length="0.05104166666666998"
            velocity="44"/>
      <Note pitch="68" beat="40.0" length="0.640625" velocity="43"/>
      <Note pitch="59" beat="40.0" length="3.0" velocity="43"/>
      <Note pitch="47" beat="40.0" length="4.0" velocity="73"/>
      <Note pitch="71" beat="40.66458333333333" length="0.6791666666666671"
            velocity="43"/>
      <Note pitch="75" beat="41.33229166666666" length="0.6166666666666671"
            velocity="47"/>
      <Note pitch="75" beat="41.94895833333333" length="0.015625" velocity="74"/>
      <Note pitch="80" beat="42.0" length="1.421875" velocity="44"/>
      <Note pitch="71" beat="42.0" length="3.796875" velocity="66"/>
      <Note pitch="75" beat="42.0" length="1.898958333333333" velocity="66"/>
      <Note pitch="59" beat="43.0" length="1.0" velocity="45"/>
      <Note pitch="78" beat="43.5" length="0.5" velocity="42"/>
      <Note pitch="76" beat="44.0" length="6.0" velocity="39"/>
      <Note pitch="59" beat="44.0" length="0.6760416666666629" velocity="42"/>
      <Note pitch="49" beat="44.0" length="3.796875" velocity="75"/>
      <Note pitch="61" beat="44.66458333333333" length="0.6791666666666671"
            velocity="45"/>
      <Note pitch="64" beat="45.33229166666666" length="0.6677083333333371"
            velocity="43"/>
      <Note pitch="64" beat="46.0" length="3.765625" velocity="59"/>
      <Note pitch="73" beat="46.0" length="1.5" velocity="87"/>
      <Note pitch="56" beat="47.0" length="1.0" velocity="33"/>
      <Note pitch="71" beat="47.5" length="0.5" velocity="89"/>
      <Note pitch="70" beat="48.0" length="2.0" velocity="42"/>
      <Note pitch="54" beat="48.0" length="0.6760416666666629" velocity="40"/>
      <Note pitch="42" beat="48.0" length="1.898958333333333" velocity="63"/>
      <Note pitch="58" beat="48.66458333333333" length="0.6322916666666671"
            velocity="41"/>
      <Note pitch="68" beat="50.0" length="1.5" velocity="32"/>
      <Note pitch="66" beat="52.0" length="0.5" velocity="34"/>
      <Note pitch="63" beat="52.5" length="0.5" velocity="43"/>
      <Note pitch="66" beat="52.5" length="0.5" velocity="43"/>
      <Note pitch="71" beat="52.5" length="0.5" velocity="43"/>
      <Note pitch="47" beat="52.5" length="0.5" velocity="35"/>
      <Note pitch="54" beat="52.5" length="0.5" velocity="35"/>
      <Note pitch="63" beat="53.5" length="0.25" velocity="43"/>
      <Note pitch="66" beat="53.5" length="0.25" velocity="43"/>
      <Note pitch="71" beat="53.5" length="0.25" velocity="43"/>
      <Note pitch="47" beat="53.5" length="0.25" velocity="41"/>
      <Note pitch="54" beat="53.5" length="0.25" velocity="41"/>
      <Note pitch="63" beat="54.0" length="0.234375" velocity="43"/>
      <Note pitch="66" beat="54.0" length="0.234375" velocity="43"/>
      <Note pitch="71" beat="54.0" length="0.234375" velocity="43"/>
      <Note pitch="47" beat="54.0" length="0.234375" velocity="37"/>
      <Note pitch="54" beat="54.0" length="0.234375" velocity="37"/>
      <Note pitch="64" beat="54.5" length="0.5" velocity="35"/>
      <Note pitch="66" beat="54.5" length="0.5" velocity="35"/>
      <Note pitch="70" beat="54.5" length="0.5083333333333329" velocity="35"/>
      <Note pitch="49" beat="54.5" length="0.5083333333333329" velocity="41"/>
      <Note pitch="54" beat="54.5" length="0.5" velocity="41"/>
      <Note pitch="64" beat="55.5" length="0.25" velocity="45"/>
      <Note pitch="66" beat="55.5" length="0.25" velocity="45"/>
      <Note pitch="71" beat="55.5" length="0.2541666666666629" velocity="45"/>
      <Note pitch="47" beat="55.5" length="0.2541666666666629" velocity="37"/>
      <Note pitch="54" beat="55.5" length="0.25" velocity="37"/>
      <Note pitch="64" beat="56.0" length="0.234375" velocity="37"/>
      <Note pitch="66" beat="56.0" length="0.234375" velocity="37"/>
      <Note pitch="73" beat="56.0" length="0.234375" velocity="37"/>
      <Note pitch="46" beat="56.0" length="0.234375" velocity="39"/>
      <Note pitch="54" beat="56.0" length="0.234375" velocity="39"/>
      <Note pitch="64" beat="56.5" length="4.0" velocity="41"/>
      <Note pitch="66" beat="56.5" length="4.0" velocity="41"/>
      <Note pitch="73" beat="56.5" length="4.0" velocity="41"/>
      <Note pitch="46" beat="56.5" length="4.0" velocity="44"/>
      <Note pitch="54" beat="56.5" length="4.0" velocity="44"/>
      <Note pitch="63" beat="60.5" length="0.5" velocity="19"/>
      <Note pitch="66" beat="60.5" length="0.5" velocity="19"/>
      <Note pitch="71" beat="60.5" length="0.5" velocity="19"/>
      <Note pitch="47" beat="60.5" length="0.5" velocity="16"/>
      <Note pitch="54" beat="60.5" length="0.5" velocity="16"/>
      <Note pitch="63" beat="61.5" length="0.25" velocity="19"/>
      <Note pitch="66" beat="61.5" length="0.25" velocity="19"/>
      <Note pitch="71" beat="61.5" length="0.25" velocity="19"/>
      <Note pitch="47" beat="61.5" length="0.25" velocity="22"/>
      <Note pitch="54" beat="61.5" length="0.25" velocity="22"/>
      <Note pitch="63" beat="62.0" length="0.234375" velocity="17"/>
      <Note pitch="66" beat="62.0" length="0.234375" velocity="17"/>
      <Note pitch="71" beat="62.0" length="0.234375" velocity="17"/>
      <Note pitch="47" beat="62.0" length="0.234375" velocity="18"/>
      <Note pitch="54" beat="62.0" length="0.234375" velocity="18"/>
      <Note pitch="63" beat="62.5" length="0.2541666666666629" velocity="20"/>
      <Note pitch="66" beat="62.5" length="0.25" velocity="20"/>
      <Note pitch="71" beat="62.5" length="0.2541666666666629" velocity="20"/>
      <Note pitch="47" beat="62.5" length="0.2541666666666629" velocity="24"/>
      <Note pitch="54" beat="62.5" length="0.25" velocity="24"/>
      <Note pitch="64" beat="63.0" length="0.25" velocity="25"/>
      <Note pitch="66" beat="63.0" length="0.25" velocity="25"/>
      <Note pitch="70" beat="63.0" length="0.2541666666666629" velocity="25"/>
      <Note pitch="49" beat="63.0" length="0.2541666666666629" velocity="19"/>
      <Note pitch="54" beat="63.0" length="0.25" velocity="19"/>
      <Note pitch="64" beat="63.5" length="0.375" velocity="21"/>
      <Note pitch="66" beat="63.5" length="0.375" velocity="21"/>
      <Note pitch="71" beat="63.5" length="0.3791666666666629" velocity="21"/>
      <Note pitch="47" beat="63.5" length="0.3791666666666629" velocity="19"/>
      <Note pitch="54" beat="63.5" length="0.375" velocity="19"/>
      <Note pitch="64" beat="64.25" length="0.1177083333333258" velocity="22"/>
      <Note pitch="66" beat="64.25" length="0.1177083333333258" velocity="22"/>
      <Note pitch="73" beat="64.25" length="0.1177083333333258" velocity="22"/>
      <Note pitch="46" beat="64.25" length="0.1177083333333258" velocity="14"/>
      <Note pitch="54" beat="64.25" length="0.1177083333333258" velocity="14"/>
      <Note pitch="64" beat="64.5" length="3.0" velocity="22"/>
      <Note pitch="66" beat="64.5" length="3.0" velocity="22"/>
      <Note pitch="73" beat="64.5" length="3.0" velocity="22"/>
      <Note pitch="46" beat="64.5" length="4.0" velocity="19"/>
      <Note pitch="54" beat="64.5" length="4.0" velocity="19"/>
      <Note pitch="66" beat="67.5" length="1.019791666666663" velocity="17"/>
      <Note pitch="75" beat="68.5" length="1.5" velocity="23"/>
      <Note pitch="63" beat="68.5" length="3.948958333333337" velocity="52"/>
      <Note pitch="54" beat="68.5" length="3.0" velocity="19"/>
      <Note pitch="47" beat="68.5" length="4.0" velocity="57"/>
      <Note pitch="75" beat="70.0" length="0.5" velocity="17"/>
      <Note pitch="75" beat="70.5" length="1.527083333333337" velocity="22"/>
      <Note pitch="55" beat="71.5" length="1.0" velocity="18"/>
      <Note pitch="70" beat="72.0" length="0.5083333333333258" velocity="19"/>
      <Note pitch="63" beat="72.44895833333334" length="0.05104166666666288"
            velocity="58"/>
      <Note pitch="73" beat="72.5" length="1.933333333333337" velocity="18"/>
      <Note pitch="63" beat="72.5" length="3.605208333333337" velocity="60"/>
      <Note pitch="56" beat="72.5" length="3.0" velocity="21"/>
      <Note pitch="47" beat="72.5" length="4.0" velocity="62"/>
      <Note pitch="71" beat="74.5" length="1.019791666666663" velocity="18"/>
      <Note pitch="70" beat="75.5" length="0.9489583333333371" velocity="17"/>
      <Note pitch="58" beat="75.5" length="1.0" velocity="20"/>
      <Note pitch="63" beat="76.44895833333334" length="0.05104166666666288"
            velocity="27"/>
      <Note pitch="68" beat="76.5" length="0.640625" velocity="25"/>
      <Note pitch="59" beat="76.5" length="3.0" velocity="19"/>
      <Note pitch="47" beat="76.5" length="4.0" velocity="55"/>
      <Note pitch="71" beat="77.16458333333333" length="0.6791666666666742"
            velocity="18"/>
      <Note pitch="75" beat="77.83229166666666" length="2.53125" velocity="23"/>
      <Note pitch="80" beat="78.5" length="1.5" velocity="26"/>
      <Note pitch="71" beat="78.5" length="4.0" velocity="52"/>
      <Note pitch="59" beat="79.5" length="1.0" velocity="22"/>
      <Note pitch="78" beat="80.0" length="0.5" velocity="20"/>
      <Note pitch="76" beat="80.5" length="6.0" velocity="17"/>
      <Note pitch="59" beat="80.5" length="0.6760416666666629" velocity="19"/>
      <Note pitch="49" beat="80.5" length="3.796875" velocity="57"/>
      <Note pitch="61" beat="81.16458333333333" length="0.6791666666666742"
            velocity="24"/>
      <Note pitch="64" beat="81.83229166666666" length="0.6677083333333371"
            velocity="24"/>
      <Note pitch="64" beat="82.5" length="4.0" velocity="56"/>
      <Note pitch="73" beat="82.5" length="1.5" velocity="73"/>
      <Note pitch="56" beat="83.5" length="1.0" velocity="20"/>
      <Note pitch="71" beat="84.0" length="0.5" velocity="77"/>
      <Note pitch="70" beat="84.5" length="3.5" velocity="18"/>
      <Note pitch="54" beat="84.5" length="3.5" velocity="19"/>
      <Note pitch="42" beat="84.5" length="2.0" velocity="54"/>
      <Note pitch="58" beat="85.0" length="3.0" velocity="22"/>
      <Note pitch="61" beat="85.5" length="2.5" velocity="18"/>
      <Note pitch="67" beat="86.5" length="1.5" velocity="17"/>
      <Note pitch="74" beat="88.0" length="1.0" velocity="53"/>
      <Note pitch="79" beat="88.0" length="1.0" velocity="53"/>
      <Note pitch="83" beat="88.0" length="1.0" velocity="53"/>
      <Note pitch="67" beat="88.0" length="1.0" velocity="45"/>
      <Note pitch="71" beat="88.0" length="1.0" velocity="45"/>
      <Note pitch="75" beat="89.0" length="1.0" velocity="44"/>
      <Note pitch="80" beat="89.0" length="1.0" velocity="44"/>
      <Note pitch="83" beat="89.0" length="1.0" velocity="44"/>
      <Note pitch="67" beat="89.0" length="1.0" velocity="39"/>
      <Note pitch="71" beat="89.0" length="1.0" velocity="39"/>
      <Note pitch="75" beat="90.0" length="1.0" velocity="38"/>
      <Note pitch="80" beat="90.0" length="1.0" velocity="38"/>
      <Note pitch="83" beat="90.0" length="1.0" velocity="38"/>
      <Note pitch="67" beat="90.0" length="1.0" velocity="37"/>
      <Note pitch="71" beat="90.0" length="1.0" velocity="37"/>
      <Note pitch="75" beat="91.0" length="0.6645833333333258" velocity="38"/>
      <Note pitch="80" beat="91.0" length="0.6645833333333258" velocity="38"/>
      <Note pitch="83" beat="91.0" length="0.6645833333333258" velocity="38"/>
      <Note pitch="67" beat="91.0" length="0.6645833333333258" velocity="36"/>
      <Note pitch="71" beat="91.0" length="0.6645833333333258" velocity="36"/>
      <Note pitch="75" beat="91.66458333333333" length="0.6677083333333371"
            velocity="37"/>
      <Note pitch="80" beat="91.66458333333333" length="0.6677083333333371"
            velocity="37"/>
      <Note pitch="83" beat="91.66458333333333" length="0.6677083333333371"
            velocity="37"/>
      <Note pitch="67" beat="91.66458333333333" length="0.6677083333333371"
            velocity="39"/>
      <Note pitch="71" beat="91.66458333333333" length="0.6677083333333371"
            velocity="39"/>
      <Note pitch="75" beat="92.33229166666666" length="0.6677083333333371"
            velocity="38"/>
      <Note pitch="80" beat="92.33229166666666" length="0.6677083333333371"
            velocity="38"/>
      <Note pitch="83" beat="92.33229166666666" length="0.6677083333333371"
            velocity="38"/>
      <Note pitch="67" beat="92.33229166666666" length="0.6677083333333371"
            velocity="40"/>
      <Note pitch="71" beat="92.33229166666666" length="0.6677083333333371"
            velocity="40"/>
      <Note pitch="59" beat="92.94166666666666" length="0.05833333333333712"
            velocity="61"/>
      <Note pitch="74" beat="93.0" length="2.0" velocity="45"/>
      <Note pitch="79" beat="93.0" length="2.0" velocity="45"/>
      <Note pitch="86" beat="93.0" length="2.0" velocity="45"/>
      <Note pitch="67" beat="93.0" length="1.898958333333326" velocity="43"/>
      <Note pitch="71" beat="93.0" length="1.898958333333326" velocity="43"/>
      <Note pitch="59" beat="93.0" length="1.933333333333337" velocity="60"/>
      <Note pitch="63" beat="94.94583333333333" length="1.003125000000011"
            velocity="64"/>
      <Note pitch="74" beat="95.0" length="1.0" velocity="38"/>
      <Note pitch="79" beat="95.0" length="1.0" velocity="38"/>
      <Note pitch="83" beat="95.0" length="1.0" velocity="38"/>
      <Note pitch="67" beat="95.0" length="0.9489583333333371" velocity="37"/>
      <Note pitch="71" beat="95.0" length="0.9489583333333371" velocity="37"/>
      <Note pitch="76" beat="96.0" length="1.0" velocity="37"/>
      <Note pitch="79" beat="96.0" length="1.0" velocity="37"/>
      <Note pitch="81" beat="96.0" length="1.0" velocity="37"/>
      <Note pitch="60" beat="96.0" length="1.0" velocity="42"/>
      <Note pitch="67" beat="96.0" length="1.0" velocity="42"/>
      <Note pitch="69" beat="96.0" length="1.0" velocity="42"/>
      <Note pitch="76" beat="97.0" length="1.0" velocity="40"/>
      <Note pitch="79" beat="97.0" length="1.0" velocity="40"/>
      <Note pitch="81" beat="97.0" length="1.0" velocity="40"/>
      <Note pitch="60" beat="97.0" length="1.0" velocity="37"/>
      <Note pitch="67" beat="97.0" length="1.0" velocity="37"/>
      <Note pitch="69" beat="97.0" length="1.0" velocity="37"/>
      <Note pitch="76" beat="98.0" length="1.0" velocity="43"/>
      <Note pitch="79" beat="98.0" length="1.0" velocity="43"/>
      <Note pitch="81" beat="98.0" length="1.0" velocity="43"/>
      <Note pitch="60" beat="98.0" length="1.0" velocity="40"/>
      <Note pitch="67" beat="98.0" length="1.0" velocity="40"/>
      <Note pitch="69" beat="98.0" length="1.0" velocity="40"/>
      <Note pitch="76" beat="99.0" length="0.6645833333333258" velocity="37"/>
      <Note pitch="79" beat="99.0" length="0.6645833333333258" velocity="37"/>
      <Note pitch="81" beat="99.0" length="0.6645833333333258" velocity="37"/>
      <Note pitch="60" beat="99.0" length="0.6645833333333258" velocity="38"/>
      <Note pitch="67" beat="99.0" length="0.6645833333333258" velocity="38"/>
      <Note pitch="69" beat="99.0" length="0.6645833333333258" velocity="38"/>
      <Note pitch="76" beat="99.66458333333333" length="0.6677083333333371"
            velocity="47"/>
      <Note pitch="79" beat="99.66458333333333" length="0.6677083333333371"
            velocity="47"/>
      <Note pitch="83" beat="99.66458333333333" length="0.6677083333333371"
            velocity="47"/>
      <Note pitch="59" beat="99.66458333333333" length="0.6677083333333371"
            velocity="39"/>
      <Note pitch="67" beat="99.66458333333333" length="0.6677083333333371"
            velocity="39"/>
      <Note pitch="71" beat="99.66458333333333" length="0.6677083333333371"
            velocity="39"/>
      <Note pitch="76" beat="100.3322916666667" length="0.6677083333333371"
            velocity="42"/>
      <Note pitch="79" beat="100.3322916666667" length="0.6677083333333371"
            velocity="42"/>
      <Note pitch="84" beat="100.3322916666667" length="0.6677083333333371"
            velocity="42"/>
      <Note pitch="57" beat="100.3322916666667" length="0.6677083333333371"
            velocity="42"/>
      <Note pitch="67" beat="100.3322916666667" length="0.6677083333333371"
            velocity="42"/>
      <Note pitch="72" beat="100.3322916666667" length="0.6677083333333371"
            velocity="42"/>
      <Note pitch="59" beat="100.9302083333333" length="2.109375" velocity="59"/>
      <Note pitch="74" beat="101.0" length="3.0" velocity="42"/>
      <Note pitch="79" beat="101.0" length="3.0" velocity="42"/>
      <Note pitch="83" beat="101.0" length="3.0" velocity="42"/>
      <Note pitch="67" beat="101.0" length="2.847916666666663" velocity="39"/>
      <Note pitch="71" beat="101.0" length="2.847916666666663" velocity="39"/>
      <Note pitch="62" beat="103.0" length="5.698958333333337" velocity="64"/>
      <Note pitch="74" beat="104.0" length="1.0" velocity="34"/>
      <Note pitch="79" beat="104.0" length="1.0" velocity="34"/>
      <Note pitch="83" beat="104.0" length="1.0" velocity="34"/>
      <Note pitch="67" beat="104.0" length="1.0" velocity="39"/>
      <Note pitch="71" beat="104.0" length="1.0" velocity="39"/>
      <Note pitch="74" beat="105.0" length="1.0" velocity="42"/>
      <Note pitch="79" beat="105.0" length="1.0" velocity="42"/>
      <Note pitch="83" beat="105.0" length="1.0" velocity="42"/>
      <Note pitch="67" beat="105.0" length="1.0" velocity="43"/>
      <Note pitch="71" beat="105.0" length="1.0" velocity="43"/>
      <Note pitch="74" beat="106.0" length="1.0" velocity="38"/>
      <Note pitch="79" beat="106.0" length="1.0" velocity="38"/>
      <Note pitch="83" beat="106.0" length="1.0" velocity="38"/>
      <Note pitch="67" beat="106.0" length="1.0" velocity="37"/>
      <Note pitch="71" beat="106.0" length="1.0" velocity="37"/>
      <Note pitch="74" beat="107.0" length="0.6645833333333258" velocity="40"/>
      <Note pitch="79" beat="107.0" length="0.6645833333333258" velocity="40"/>
      <Note pitch="83" beat="107.0" length="0.6645833333333258" velocity="40"/>
      <Note pitch="67" beat="107.0" length="0.6645833333333258" velocity="40"/>
      <Note pitch="71" beat="107.0" length="0.6645833333333258" velocity="40"/>
      <Note pitch="74" beat="107.6645833333333" length="0.6677083333333371"
            velocity="42"/>
      <Note pitch="79" beat="107.6645833333333" length="0.6677083333333371"
            velocity="42"/>
      <Note pitch="83" beat="107.6645833333333" length="0.6677083333333371"
            velocity="42"/>
      <Note pitch="67" beat="107.6645833333333" length="0.6677083333333371"
            velocity="35"/>
      <Note pitch="71" beat="107.6645833333333" length="0.6677083333333371"
            velocity="35"/>
      <Note pitch="74" beat="108.3322916666667" length="0.6677083333333371"
            velocity="43"/>
      <Note pitch="79" beat="108.3322916666667" length="0.6677083333333371"
            velocity="43"/>
      <Note pitch="83" beat="108.3322916666667" length="0.6677083333333371"
            velocity="43"/>
      <Note pitch="67" beat="108.3322916666667" length="0.6677083333333371"
            velocity="40"/>
      <Note pitch="71" beat="108.3322916666667" length="0.6677083333333371"
            velocity="40"/>
      <Note pitch="59" beat="108.9416666666667" length="0.05833333333333712"
            velocity="61"/>
      <Note pitch="74" beat="109.0" length="2.0" velocity="42"/>
      <Note pitch="79" beat="109.0" length="2.0" velocity="42"/>
      <Note pitch="86" beat="109.0" length="2.0" velocity="42"/>
      <Note pitch="67" beat="109.0" length="1.898958333333326" velocity="40"/>
      <Note pitch="71" beat="109.0" length="1.898958333333326" velocity="40"/>
      <Note pitch="59" beat="109.0" length="1.933333333333337" velocity="59"/>
      <Note pitch="63" beat="110.9458333333333" length="1.003125000000011"
            velocity="61"/>
      <Note pitch="74" beat="111.0" length="1.0" velocity="35"/>
      <Note pitch="79" beat="111.0" length="1.0" velocity="35"/>
      <Note pitch="83" beat="111.0" length="1.0" velocity="35"/>
      <Note pitch="67" beat="111.0" length="0.9489583333333371" velocity="39"/>
      <Note pitch="71" beat="111.0" length="0.9489583333333371" velocity="39"/>
      <Note pitch="76" beat="112.0" length="1.0" velocity="40"/>
      <Note pitch="79" beat="112.0" length="1.0" velocity="40"/>
      <Note pitch="81" beat="112.0" length="1.0" velocity="40"/>
      <Note pitch="60" beat="112.0" length="1.0" velocity="39"/>
      <Note pitch="67" beat="112.0" length="1.0" velocity="39"/>
      <Note pitch="69" beat="112.0" length="1.0" velocity="39"/>
      <Note pitch="76" beat="113.0" length="1.0" velocity="40"/>
      <Note pitch="79" beat="113.0" length="1.0" velocity="40"/>
      <Note pitch="81" beat="113.0" length="1.0" velocity="40"/>
      <Note pitch="60" beat="113.0" length="1.0" velocity="39"/>
      <Note pitch="67" beat="113.0" length="1.0" velocity="39"/>
      <Note pitch="69" beat="113.0" length="1.0" velocity="39"/>
      <Note pitch="76" beat="114.0" length="1.0" velocity="41"/>
      <Note pitch="79" beat="114.0" length="1.0" velocity="41"/>
      <Note pitch="81" beat="114.0" length="1.0" velocity="41"/>
      <Note pitch="60" beat="114.0" length="1.0" velocity="37"/>
      <Note pitch="67" beat="114.0" length="1.0" velocity="37"/>
      <Note pitch="69" beat="114.0" length="1.0" velocity="37"/>
      <Note pitch="76" beat="115.0" length="0.6645833333333258" velocity="41"/>
      <Note pitch="79" beat="115.0" length="0.6645833333333258" velocity="41"/>
      <Note pitch="81" beat="115.0" length="0.6645833333333258" velocity="41"/>
      <Note pitch="60" beat="115.0" length="0.6645833333333258" velocity="35"/>
      <Note pitch="67" beat="115.0" length="0.6645833333333258" velocity="35"/>
      <Note pitch="69" beat="115.0" length="0.6645833333333258" velocity="35"/>
      <Note pitch="76" beat="115.6645833333333" length="0.6677083333333371"
            velocity="41"/>
      <Note pitch="79" beat="115.6645833333333" length="0.6677083333333371"
            velocity="41"/>
      <Note pitch="83" beat="115.6645833333333" length="0.6677083333333371"
            velocity="41"/>
      <Note pitch="59" beat="115.6645833333333" length="0.6677083333333371"
            velocity="41"/>
      <Note pitch="67" beat="115.6645833333333" length="0.6677083333333371"
            velocity="41"/>
      <Note pitch="71" beat="115.6645833333333" length="0.6677083333333371"
            velocity="41"/>
      <Note pitch="76" beat="116.3322916666667" length="0.6677083333333371"
            velocity="40"/>
      <Note pitch="79" beat="116.3322916666667" length="0.6677083333333371"
            velocity="40"/>
      <Note pitch="84" beat="116.3322916666667" length="0.6677083333333371"
            velocity="40"/>
      <Note pitch="57" beat="116.3322916666667" length="0.6677083333333371"
            velocity="42"/>
      <Note pitch="67" beat="116.3322916666667" length="0.6677083333333371"
            velocity="42"/>
      <Note pitch="72" beat="116.3322916666667" length="0.6677083333333371"
            velocity="42"/>
      <Note pitch="59" beat="116.9302083333333" length="2.109375" velocity="63"/>
      <Note pitch="74" beat="117.0" length="3.0" velocity="37"/>
      <Note pitch="79" beat="117.0" length="3.0" velocity="37"/>
      <Note pitch="83" beat="117.0" length="3.0" velocity="37"/>
      <Note pitch="67" beat="117.0" length="2.847916666666663" velocity="38"/>
      <Note pitch="71" beat="117.0" length="2.847916666666663" velocity="38"/>
      <Note pitch="62" beat="119.0" length="0.9489583333333371" velocity="68"/>
      <Note pitch="66" beat="120.75" length="0.5" velocity="35"/>
      <Note pitch="54" beat="120.75" length="0.5" velocity="34"/>
      <Note pitch="63" beat="121.25" length="0.5" velocity="43"/>
      <Note pitch="66" beat="121.25" length="0.5" velocity="43"/>
      <Note pitch="71" beat="121.25" length="0.5" velocity="43"/>
      <Note pitch="47" beat="121.25" length="0.5" velocity="40"/>
      <Note pitch="54" beat="121.25" length="0.5" velocity="40"/>
      <Note pitch="63" beat="122.25" length="0.25" velocity="39"/>
      <Note pitch="66" beat="122.25" length="0.25" velocity="39"/>
      <Note pitch="71" beat="122.25" length="0.25" velocity="39"/>
      <Note pitch="47" beat="122.25" length="0.25" velocity="38"/>
      <Note pitch="54" beat="122.25" length="0.25" velocity="38"/>
      <Note pitch="63" beat="122.75" length="0.234375" velocity="37"/>
      <Note pitch="66" beat="122.75" length="0.234375" velocity="37"/>
      <Note pitch="71" beat="122.75" length="0.234375" velocity="37"/>
      <Note pitch="47" beat="122.75" length="0.234375" velocity="40"/>
      <Note pitch="54" beat="122.75" length="0.234375" velocity="40"/>
      <Note pitch="64" beat="123.25" length="0.5" velocity="41"/>
      <Note pitch="66" beat="123.25" length="0.5" velocity="41"/>
      <Note pitch="70" beat="123.25" length="0.5083333333333258" velocity="41"/>
      <Note pitch="49" beat="123.25" length="0.5083333333333258" velocity="36"/>
      <Note pitch="54" beat="123.25" length="0.5" velocity="36"/>
      <Note pitch="64" beat="124.25" length="0.25" velocity="41"/>
      <Note pitch="66" beat="124.25" length="0.25" velocity="41"/>
      <Note pitch="71" beat="124.25" length="0.2541666666666629" velocity="41"/>
      <Note pitch="47" beat="124.25" length="0.2541666666666629" velocity="40"/>
      <Note pitch="54" beat="124.25" length="0.25" velocity="40"/>
      <Note pitch="64" beat="124.75" length="0.234375" velocity="38"/>
      <Note pitch="66" beat="124.75" length="0.234375" velocity="38"/>
      <Note pitch="73" beat="124.75" length="0.234375" velocity="38"/>
      <Note pitch="46" beat="124.75" length="0.234375" velocity="39"/>
      <Note pitch="54" beat="124.75" length="0.234375" velocity="39"/>
      <Note pitch="64" beat="125.25" length="3.0" velocity="38"/>
      <Note pitch="66" beat="125.25" length="3.0" velocity="38"/>
      <Note pitch="73" beat="125.25" length="3.0" velocity="38"/>
      <Note pitch="46" beat="125.25" length="3.0" velocity="35"/>
      <Note pitch="54" beat="125.25" length="3.0" velocity="35"/>
      <Note pitch="66" beat="128.75" length="0.5" velocity="39"/>
      <Note pitch="54" beat="128.75" length="0.5" velocity="37"/>
      <Note pitch="63" beat="129.25" length="0.75" velocity="42"/>
      <Note pitch="66" beat="129.25" length="0.75" velocity="42"/>
      <Note pitch="71" beat="129.25" length="0.75" velocity="42"/>
      <Note pitch="47" beat="129.25" length="0.75" velocity="36"/>
      <Note pitch="54" beat="129.25" length="0.75" velocity="36"/>
      <Note pitch="63" beat="130.75" length="0.234375" velocity="39"/>
      <Note pitch="66" beat="130.75" length="0.234375" velocity="39"/>
      <Note pitch="71" beat="130.75" length="0.234375" velocity="39"/>
      <Note pitch="47" beat="130.75" length="0.234375" velocity="39"/>
      <Note pitch="54" beat="130.75" length="0.234375" velocity="39"/>
      <Note pitch="63" beat="131.25" length="0.2541666666666629" velocity="39"/>
      <Note pitch="66" beat="131.25" length="0.25" velocity="39"/>
      <Note pitch="71" beat="131.25" length="0.2541666666666629" velocity="39"/>
      <Note pitch="47" beat="131.25" length="0.2541666666666629" velocity="40"/>
      <Note pitch="54" beat="131.25" length="0.25" velocity="40"/>
      <Note pitch="64" beat="131.75" length="0.25" velocity="37"/>
      <Note pitch="66" beat="131.75" length="0.25" velocity="37"/>
      <Note pitch="70" beat="131.75" length="0.2541666666666629" velocity="37"/>
      <Note pitch="49" beat="131.75" length="0.2541666666666629" velocity="39"/>
      <Note pitch="54" beat="131.75" length="0.25" velocity="39"/>
      <Note pitch="64" beat="132.25" length="0.3552083333333371" velocity="42"/>
      <Note pitch="66" beat="132.25" length="0.3552083333333371" velocity="42"/>
      <Note pitch="71" beat="132.25" length="0.3552083333333371" velocity="42"/>
      <Note pitch="47" beat="132.25" length="0.3552083333333371" velocity="41"/>
      <Note pitch="54" beat="132.25" length="0.3552083333333371" velocity="41"/>
      <Note pitch="64" beat="133.0" length="0.125" velocity="40"/>
      <Note pitch="66" beat="133.0" length="0.125" velocity="40"/>
      <Note pitch="73" beat="133.0" length="0.125" velocity="40"/>
      <Note pitch="46" beat="133.0" length="0.125" velocity="42"/>
      <Note pitch="54" beat="133.0" length="0.125" velocity="42"/>
      <Note pitch="64" beat="133.25" length="3.0" velocity="42"/>
      <Note pitch="66" beat="133.25" length="3.0" velocity="42"/>
      <Note pitch="73" beat="133.25" length="3.0" velocity="42"/>
      <Note pitch="46" beat="133.25" length="3.0" velocity="40"/>
      <Note pitch="54" beat="133.25" length="3.0" velocity="40"/>
      <Note pitch="66" beat="136.25" length="1.0" velocity="33"/>
      <Note pitch="54" beat="136.25" length="1.0" velocity="39"/>
      <Note pitch="63" beat="137.2072916666667" length="0.04270833333333712"
            velocity="63"/>
      <Note pitch="75" beat="137.25" length="1.421875" velocity="51"/>
      <Note pitch="63" beat="137.25" length="3.796875" velocity="60"/>
      <Note pitch="54" beat="137.25" length="3.0" velocity="34"/>
      <Note pitch="47" beat="137.25" length="4.0" velocity="51"/>
      <Note pitch="75" beat="138.75" length="0.5" velocity="40"/>
      <Note pitch="75" beat="139.25" length="1.5" velocity="35"/>
      <Note pitch="55" beat="140.25" length="1.0" velocity="38"/>
      <Note pitch="70" beat="140.75" length="0.5" velocity="34"/>
      <Note pitch="73" beat="141.25" length="2.0" velocity="44"/>
      <Note pitch="63" beat="141.25" length="3.0" velocity="57"/>
      <Note pitch="47" beat="141.25" length="3.0" velocity="37"/>
      <Note pitch="56" beat="141.25" length="3.0" velocity="37"/>
      <Note pitch="71" beat="143.25" length="1.0" velocity="34"/>
      <Note pitch="64" beat="145.25" length="1.0" velocity="52"/>
      <Note pitch="49" beat="145.25" length="1.0" velocity="54"/>
      <Note pitch="68" beat="145.3208333333333" length="0.9291666666666742"
            velocity="52"/>
      <Note pitch="56" beat="145.3208333333333" length="0.9291666666666742"
            velocity="54"/>
      <Note pitch="64" beat="147.2072916666667" length="0.04270833333333712"
            velocity="71"/>
      <Note pitch="64" beat="147.25" length="0.2385416666666629" velocity="72"/>
      <Note pitch="71" beat="147.25" length="0.2385416666666629" velocity="72"/>
      <Note pitch="49" beat="147.25" length="0.2541666666666629" velocity="56"/>
      <Note pitch="59" beat="147.25" length="0.2541666666666629" velocity="56"/>
      <Note pitch="70" beat="148.75" length="0.234375" velocity="55"/>
      <Note pitch="58" beat="148.75" length="0.234375" velocity="54"/>
      <Note pitch="63" beat="149.25" length="0.5083333333333258" velocity="53"/>
      <Note pitch="67" beat="149.25" length="0.5083333333333258" velocity="53"/>
      <Note pitch="51" beat="149.25" length="0.5083333333333258" velocity="60"/>
      <Note pitch="58" beat="149.25" length="0.5083333333333258" velocity="60"/>
      <Note pitch="63" beat="151.25" length="0.4729166666666629" velocity="56"/>
      <Note pitch="66" beat="151.25" length="0.4729166666666629" velocity="56"/>
      <Note pitch="48" beat="151.25" length="0.4729166666666629" velocity="55"/>
      <Note pitch="57" beat="151.25" length="0.4729166666666629" velocity="55"/>
      <Note pitch="61" beat="153.25" length="1.0" velocity="54"/>
      <Note pitch="64" beat="153.25" length="1.0" velocity="54"/>
      <Note pitch="56" beat="153.25" length="1.527083333333337" velocity="54"/>
      <Note pitch="49" beat="153.25" length="1.019791666666663" velocity="67"/>
      <Note pitch="55" beat="154.75" length="0.4729166666666629" velocity="63"/>
      <Note pitch="58" beat="155.1447916666667" length="2.004166666666663"
            velocity="67"/>
      <Note pitch="64" beat="155.1447916666667" length="2.004166666666663"
            velocity="67"/>
      <Note pitch="68" beat="155.25" length="1.527083333333337" velocity="67"/>
      <Note pitch="42" beat="155.25" length="1.5" velocity="59"/>
      <Note pitch="54" beat="155.25" length="1.5" velocity="59"/>
      <Note pitch="66" beat="156.75" length="0.4145833333333258" velocity="59"/>
      <Note pitch="54" beat="156.75" length="0.5" velocity="64"/>
      <Note pitch="59" beat="157.1645833333333" length="2.085416666666674"
            velocity="96"/>
      <Note pitch="63" beat="157.25" length="2.0" velocity="96"/>
      <Note pitch="66" beat="157.25" length="2.0" velocity="96"/>
      <Note pitch="71" beat="157.25" length="2.0" velocity="96"/>
      <Note pitch="47" beat="157.25" length="2.0" velocity="84"/>
      <Note pitch="54" beat="157.25" length="2.0" velocity="84"/>
      <Note pitch="70" beat="159.25" length="0.5083333333333258" velocity="85"/>
      <Note pitch="64" beat="159.25" length="1.898958333333326" velocity="58"/>
      <Note pitch="66" beat="159.25" length="1.898958333333326" velocity="58"/>
      <Note pitch="49" beat="159.25" length="2.0" velocity="79"/>
      <Note pitch="54" beat="159.25" length="2.0" velocity="79"/>
      <Note pitch="76" beat="159.75" length="1.019791666666663" velocity="96"/>
      <Note pitch="75" beat="160.75" length="0.4302083333333258" velocity="67"/>
      <Note pitch="63" beat="161.1802083333333" length="2.069791666666674"
            velocity="83"/>
      <Note pitch="66" beat="161.25" length="2.0" velocity="71"/>
      <Note pitch="71" beat="161.25" length="2.0" velocity="71"/>
      <Note pitch="75" beat="161.25" length="2.0" velocity="71"/>
      <Note pitch="47" beat="161.25" length="2.0" velocity="70"/>
      <Note pitch="54" beat="161.25" length="2.0" velocity="70"/>
      <Note pitch="64" beat="163.25" length="0.5083333333333258" velocity="62"/>
      <Note pitch="68" beat="163.25" length="0.5" velocity="62"/>
      <Note pitch="70" beat="163.25" length="0.5083333333333258" velocity="62"/>
      <Note pitch="73" beat="163.25" length="0.5083333333333258" velocity="62"/>
      <Note pitch="49" beat="163.25" length="1.527083333333337" velocity="66"/>
      <Note pitch="54" beat="163.25" length="1.527083333333337" velocity="66"/>
      <Note pitch="68" beat="163.75" length="1.019791666666663" velocity="70"/>
      <Note pitch="80" beat="163.75" length="1.019791666666663" velocity="70"/>
      <Note pitch="67" beat="164.75" length="0.4729166666666629" velocity="59"/>
      <Note pitch="79" beat="164.75" length="0.4729166666666629" velocity="59"/>
      <Note pitch="55" beat="164.75" length="0.4729166666666629" velocity="62"/>
      <Note pitch="66" beat="165.25" length="0.5083333333333258" velocity="45"/>
      <Note pitch="67" beat="165.25" length="1.898958333333326" velocity="24"/>
      <Note pitch="79" beat="165.25" length="1.898958333333326" velocity="24"/>
      <Note pitch="55" beat="165.25" length="0.5083333333333258" velocity="59"/>
      <Note pitch="51" beat="165.25" length="1.898958333333326" velocity="21"/>
      <Note pitch="73" beat="165.75" length="1.019791666666663" velocity="71"/>
      <Note pitch="61" beat="165.75" length="1.019791666666663" velocity="73"/>
      <Note pitch="72" beat="166.75" length="0.4729166666666629" velocity="57"/>
      <Note pitch="60" beat="166.75" length="0.4729166666666629" velocity="60"/>
      <Note pitch="72" beat="167.25" length="0.5083333333333258" velocity="63"/>
      <Note pitch="66" beat="167.25" length="0.5" velocity="19"/>
      <Note pitch="78" beat="167.25" length="0.5" velocity="19"/>
      <Note pitch="60" beat="167.25" length="1.898958333333326" velocity="66"/>
      <Note pitch="56" beat="167.25" length="1.898958333333326" velocity="22"/>
      <Note pitch="78" beat="167.75" length="0.5197916666666629" velocity="71"/>
      <Note pitch="66" beat="167.75" length="0.5197916666666629" velocity="77"/>
      <Note pitch="77" beat="168.75" length="0.4729166666666629" velocity="64"/>
      <Note pitch="65" beat="168.75" length="0.4729166666666629" velocity="59"/>
      <Note pitch="71" beat="169.25" length="0.5083333333333258" velocity="57"/>
      <Note pitch="65" beat="169.25" length="2.039583333333326" velocity="18"/>
      <Note pitch="77" beat="169.25" length="2.039583333333326" velocity="18"/>
      <Note pitch="59" beat="169.25" length="0.5083333333333258" velocity="57"/>
      <Note pitch="49" beat="169.25" length="2.039583333333326" velocity="15"/>
      <Note pitch="75" beat="169.75" length="1.019791666666663" velocity="67"/>
      <Note pitch="63" beat="169.75" length="1.019791666666663" velocity="66"/>
      <Note pitch="73" beat="170.75" length="0.5" velocity="54"/>
      <Note pitch="61" beat="170.75" length="0.5" velocity="59"/>
      <Note pitch="71" beat="171.25" length="0.5083333333333258" velocity="61"/>
      <Note pitch="64" beat="171.25" length="1.898958333333326" velocity="20"/>
      <Note pitch="73" beat="171.25" length="1.898958333333326" velocity="20"/>
      <Note pitch="76" beat="171.25" length="1.898958333333326" velocity="20"/>
      <Note pitch="59" beat="171.25" length="0.5083333333333258" velocity="61"/>
      <Note pitch="54" beat="171.25" length="1.5" velocity="23"/>
      <Note pitch="61" beat="171.25" length="1.898958333333326" velocity="23"/>
      <Note pitch="70" beat="171.75" length="0.5083333333333258" velocity="58"/>
      <Note pitch="58" beat="171.75" length="0.5083333333333258" velocity="58"/>
      <Note pitch="68" beat="172.25" length="0.5083333333333258" velocity="57"/>
      <Note pitch="56" beat="172.25" length="0.5083333333333258" velocity="69"/>
      <Note pitch="66" beat="172.75" length="0.4729166666666629" velocity="53"/>
      <Note pitch="54" beat="172.75" length="0.3989583333333258" velocity="65"/>
      <Note pitch="64" beat="173.25" length="4.078125" velocity="72"/>
      <Note pitch="70" beat="173.25" length="4.078125" velocity="72"/>
      <Note pitch="73" beat="173.25" length="4.078125" velocity="72"/>
      <Note pitch="76" beat="173.25" length="4.078125" velocity="72"/>
      <Note pitch="61" beat="173.25" length="3.5" velocity="74"/>
      <Note pitch="47" beat="173.25" length="8.0" velocity="20"/>
      <Note pitch="54" beat="173.25" length="8.0" velocity="20"/>
      <Note pitch="62" beat="176.75" length="0.5" velocity="44"/>
      <Note pitch="63" beat="177.25" length="3.796875" velocity="38"/>
      <Note pitch="71" beat="177.25" length="3.796875" velocity="38"/>
      <Note pitch="75" beat="177.25" length="3.796875" velocity="38"/>
    </MidiBlock>
  </MidiTrack>
  <AudioTrack id="1037"/>
</Music>
