<?xml version="1.0" encoding="UTF-8"?>

<Music creationTime="20 Dec 2021 11:10:00" lastModifiedTime="1 Jan 1970 8:00:00">
  <TempoTrack>
    <Tempo startBeat="0.0" bpm="79.99978666723555"/>
    <TimeSig startBeat="0.0" sigBeat="4" sigBeatsType="4"/>
  </TempoTrack>
  <PitchTrack>
    <Pitch startBeat="0.0" pitch="60"/>
  </PitchTrack>
  <MarkerTrack id="1015" name="&#26631;&#35760;"/>
  <ChordTrack name="&#26609;&#24335;&#21644;&#24358;&#36827;&#34892;" id="1069"/>
  <MidiTrack id="1020" name="Piano">
    <MidiBlock name="Piano" length="47.24856349583333" id="1079" startBeat="0.0">
      <Note pitch="64" beat="0.0" length="1.997916666666667" velocity="80"/>
      <Note pitch="72" beat="0.0" length="1.997916666666667" velocity="80"/>
      <Note pitch="72" beat="2.5" length="0.4979166666666668" velocity="80"/>
      <Note pitch="76" beat="2.5" length="0.4979166666666668" velocity="80"/>
      <Note pitch="72" beat="3.0" length="0.4979166666666668" velocity="80"/>
      <Note pitch="76" beat="3.0" length="0.4979166666666668" velocity="80"/>
      <Note pitch="72" beat="3.5" length="0.4979166666666668" velocity="80"/>
      <Note pitch="76" beat="3.5" length="0.4979166666666668" velocity="80"/>
      <Note pitch="71" beat="4.0" length="0.2479166666666668" velocity="80"/>
      <Note pitch="74" beat="4.0" length="0.2479166666666668" velocity="80"/>
      <Note pitch="67" beat="4.25" length="0.2479166666666668" velocity="80"/>
      <Note pitch="69" beat="4.5" length="0.2479166666666668" velocity="80"/>
      <Note pitch="71" beat="4.75" length="0.2479166666666668" velocity="80"/>
      <Note pitch="72" beat="5.0" length="0.2479166666666668" velocity="80"/>
      <Note pitch="74" beat="5.25" length="0.2479166666666668" velocity="80"/>
      <Note pitch="76" beat="5.5" length="0.2479166666666668" velocity="80"/>
      <Note pitch="78" beat="5.75" length="0.2479166666666668" velocity="80"/>
      <Note pitch="79" beat="6.0" length="0.9979166666666668" velocity="80"/>
      <Note pitch="71" beat="8.0" length="1.997916666666667" velocity="80"/>
      <Note pitch="74" beat="8.0" length="1.997916666666667" velocity="80"/>
      <Note pitch="74" beat="10.5" length="0.4979166666666668" velocity="80"/>
      <Note pitch="77" beat="10.5" length="0.4979166666666668" velocity="80"/>
      <Note pitch="74" beat="11.0" length="0.4979166666666668" velocity="80"/>
      <Note pitch="77" beat="11.0" length="0.4979166666666668" velocity="80"/>
      <Note pitch="74" beat="11.5" length="0.4979166666666668" velocity="80"/>
      <Note pitch="77" beat="11.5" length="0.4979166666666668" velocity="80"/>
      <Note pitch="76" beat="12.0" length="0.2479166666666668" velocity="80"/>
      <Note pitch="72" beat="12.25" length="0.2479166666666668" velocity="80"/>
      <Note pitch="74" beat="12.5" length="0.2479166666666668" velocity="80"/>
      <Note pitch="76" beat="12.75" length="0.2479166666666668" velocity="80"/>
      <Note pitch="77" beat="13.0" length="0.2479166666666668" velocity="80"/>
      <Note pitch="79" beat="13.25" length="0.2479166666666668" velocity="80"/>
      <Note pitch="81" beat="13.5" length="0.2479166666666668" velocity="80"/>
      <Note pitch="83" beat="13.75" length="0.2479166666666668" velocity="80"/>
      <Note pitch="84" beat="14.0" length="0.9979166666666668" velocity="80"/>
      <Note pitch="78" beat="16.0" length="0.247916666666665" velocity="80"/>
      <Note pitch="74" beat="16.25" length="0.247916666666665" velocity="80"/>
      <Note pitch="76" beat="16.5" length="0.247916666666665" velocity="80"/>
      <Note pitch="78" beat="16.75" length="0.247916666666665" velocity="80"/>
      <Note pitch="79" beat="17.0" length="0.247916666666665" velocity="80"/>
      <Note pitch="81" beat="17.25" length="0.247916666666665" velocity="80"/>
      <Note pitch="83" beat="17.5" length="0.247916666666665" velocity="80"/>
      <Note pitch="84" beat="17.75" length="0.247916666666665" velocity="80"/>
      <Note pitch="86" beat="18.0" length="0.997916666666665" velocity="80"/>
      <Note pitch="86" beat="20.0" length="0.247916666666665" velocity="80"/>
      <Note pitch="79" beat="20.25" length="0.247916666666665" velocity="80"/>
      <Note pitch="81" beat="20.5" length="0.247916666666665" velocity="80"/>
      <Note pitch="83" beat="20.75" length="0.247916666666665" velocity="80"/>
      <Note pitch="84" beat="21.0" length="0.247916666666665" velocity="80"/>
      <Note pitch="86" beat="21.25" length="0.247916666666665" velocity="80"/>
      <Note pitch="88" beat="21.5" length="0.247916666666665" velocity="80"/>
      <Note pitch="90" beat="21.75" length="0.247916666666665" velocity="80"/>
      <Note pitch="91" beat="22.0" length="0.997916666666665" velocity="80"/>
      <Note pitch="88" beat="24.0" length="0.247916666666665" velocity="80"/>
      <Note pitch="86" beat="24.25" length="0.247916666666665" velocity="80"/>
      <Note pitch="84" beat="24.5" length="0.247916666666665" velocity="80"/>
      <Note pitch="83" beat="24.75" length="0.247916666666665" velocity="80"/>
      <Note pitch="81" beat="25.0" length="0.247916666666665" velocity="80"/>
      <Note pitch="79" beat="25.25" length="0.247916666666665" velocity="80"/>
      <Note pitch="78" beat="25.5" length="0.247916666666665" velocity="80"/>
      <Note pitch="76" beat="25.75" length="0.247916666666665" velocity="80"/>
      <Note pitch="74" beat="26.0" length="0.247916666666665" velocity="80"/>
      <Note pitch="72" beat="26.25" length="0.247916666666665" velocity="80"/>
      <Note pitch="71" beat="26.5" length="0.247916666666665" velocity="80"/>
      <Note pitch="69" beat="26.75" length="0.247916666666665" velocity="80"/>
      <Note pitch="67" beat="27.0" length="0.247916666666665" velocity="80"/>
      <Note pitch="66" beat="27.25" length="0.247916666666665" velocity="80"/>
      <Note pitch="64" beat="27.5" length="0.247916666666665" velocity="80"/>
      <Note pitch="66" beat="27.75" length="0.247916666666665" velocity="80"/>
      <Note pitch="67" beat="28.0" length="0.247916666666665" velocity="80"/>
      <Note pitch="69" beat="28.25" length="0.247916666666665" velocity="80"/>
      <Note pitch="71" beat="28.5" length="0.247916666666665" velocity="80"/>
      <Note pitch="72" beat="28.75" length="0.247916666666665" velocity="80"/>
      <Note pitch="74" beat="29.0" length="0.247916666666665" velocity="80"/>
      <Note pitch="76" beat="29.25" length="0.247916666666665" velocity="80"/>
      <Note pitch="78" beat="29.5" length="0.247916666666665" velocity="80"/>
      <Note pitch="79" beat="29.75" length="0.247916666666665" velocity="80"/>
      <Note pitch="67" beat="30.0" length="0.997916666666665" velocity="80"/>
      <Note pitch="76" beat="32.0" length="0.2479166666666686" velocity="80"/>
      <Note pitch="69" beat="32.25" length="0.2479166666666686" velocity="80"/>
      <Note pitch="71" beat="32.5" length="0.2479166666666686" velocity="80"/>
      <Note pitch="73" beat="32.75" length="0.2479166666666686" velocity="80"/>
      <Note pitch="74" beat="33.0" length="0.2479166666666686" velocity="80"/>
      <Note pitch="76" beat="33.25" length="0.2479166666666686" velocity="80"/>
      <Note pitch="77" beat="33.5" length="0.2479166666666686" velocity="80"/>
      <Note pitch="79" beat="33.75" length="0.2479166666666686" velocity="80"/>
      <Note pitch="81" beat="34.0" length="0.9979166666666686" velocity="80"/>
      <Note pitch="77" beat="36.0" length="0.2479166666666686" velocity="80"/>
      <Note pitch="74" beat="36.25" length="0.2479166666666686" velocity="80"/>
      <Note pitch="76" beat="36.5" length="0.2479166666666686" velocity="80"/>
      <Note pitch="77" beat="36.75" length="0.2479166666666686" velocity="80"/>
      <Note pitch="79" beat="37.0" length="0.2479166666666686" velocity="80"/>
      <Note pitch="81" beat="37.25" length="0.2479166666666686" velocity="80"/>
      <Note pitch="83" beat="37.5" length="0.2479166666666686" velocity="80"/>
      <Note pitch="85" beat="37.75" length="0.2479166666666686" velocity="80"/>
      <Note pitch="86" beat="38.0" length="0.9979166666666686" velocity="80"/>
      <Note pitch="74" beat="40.0" length="0.2479166666666686" velocity="80"/>
      <Note pitch="67" beat="40.25" length="0.2479166666666686" velocity="80"/>
      <Note pitch="69" beat="40.5" length="0.2479166666666686" velocity="80"/>
      <Note pitch="71" beat="40.75" length="0.2479166666666686" velocity="80"/>
      <Note pitch="72" beat="41.0" length="0.2479166666666686" velocity="80"/>
      <Note pitch="74" beat="41.25" length="0.2479166666666686" velocity="80"/>
      <Note pitch="76" beat="41.5" length="0.2479166666666686" velocity="80"/>
      <Note pitch="77" beat="41.75" length="0.2479166666666686" velocity="80"/>
      <Note pitch="79" beat="42.0" length="0.9979166666666686" velocity="80"/>
      <Note pitch="76" beat="44.0" length="0.2479166666666686" velocity="80"/>
      <Note pitch="72" beat="44.25" length="0.2479166666666686" velocity="80"/>
      <Note pitch="74" beat="44.5" length="0.2479166666666686" velocity="80"/>
      <Note pitch="76" beat="44.75" length="0.2479166666666686" velocity="80"/>
      <Note pitch="77" beat="45.0" length="0.2479166666666686" velocity="80"/>
      <Note pitch="79" beat="45.25" length="0.2479166666666686" velocity="80"/>
      <Note pitch="81" beat="45.5" length="0.2479166666666686" velocity="80"/>
      <Note pitch="83" beat="45.75" length="0.2479166666666686" velocity="80"/>
      <Note pitch="84" beat="46.0" length="0.9979166666666686" velocity="80"/>
      <Note pitch="76" beat="48.0" length="1.997916666666669" velocity="80"/>
      <Note pitch="79" beat="48.0" length="1.997916666666669" velocity="80"/>
      <Note pitch="76" beat="50.5" length="0.4979166666666686" velocity="80"/>
      <Note pitch="79" beat="50.5" length="0.4979166666666686" velocity="80"/>
      <Note pitch="84" beat="50.5" length="0.4979166666666686" velocity="80"/>
      <Note pitch="76" beat="51.0" length="0.4979166666666686" velocity="80"/>
      <Note pitch="79" beat="51.0" length="0.4979166666666686" velocity="80"/>
      <Note pitch="84" beat="51.0" length="0.4979166666666686" velocity="80"/>
      <Note pitch="76" beat="51.5" length="0.4979166666666686" velocity="80"/>
      <Note pitch="79" beat="51.5" length="0.4979166666666686" velocity="80"/>
      <Note pitch="84" beat="51.5" length="0.4979166666666686" velocity="80"/>
      <Note pitch="77" beat="52.0" length="0.9979166666666686" velocity="80"/>
      <Note pitch="81" beat="52.0" length="0.9979166666666686" velocity="80"/>
      <Note pitch="84" beat="52.0" length="0.9979166666666686" velocity="80"/>
      <Note pitch="81" beat="54.5" length="0.4979166666666686" velocity="80"/>
      <Note pitch="84" beat="54.5" length="0.4979166666666686" velocity="80"/>
      <Note pitch="89" beat="54.5" length="0.4979166666666686" velocity="80"/>
      <Note pitch="81" beat="55.0" length="0.4979166666666686" velocity="80"/>
      <Note pitch="84" beat="55.0" length="0.4979166666666686" velocity="80"/>
      <Note pitch="89" beat="55.0" length="0.4979166666666686" velocity="80"/>
      <Note pitch="81" beat="55.5" length="0.4979166666666686" velocity="80"/>
      <Note pitch="84" beat="55.5" length="0.4979166666666686" velocity="80"/>
      <Note pitch="89" beat="55.5" length="0.4979166666666686" velocity="80"/>
      <Note pitch="88" beat="56.0" length="0.2479166666666686" velocity="80"/>
      <Note pitch="91" beat="56.25" length="0.2479166666666686" velocity="80"/>
      <Note pitch="89" beat="56.5" length="0.2479166666666686" velocity="80"/>
      <Note pitch="88" beat="56.75" length="0.2479166666666686" velocity="80"/>
      <Note pitch="86" beat="57.0" length="0.2479166666666686" velocity="80"/>
      <Note pitch="84" beat="57.25" length="0.2479166666666686" velocity="80"/>
      <Note pitch="83" beat="57.5" length="0.2479166666666686" velocity="80"/>
      <Note pitch="81" beat="57.75" length="0.2479166666666686" velocity="80"/>
      <Note pitch="79" beat="58.0" length="0.2479166666666686" velocity="80"/>
      <Note pitch="77" beat="58.25" length="0.2479166666666686" velocity="80"/>
      <Note pitch="76" beat="58.5" length="0.2479166666666686" velocity="80"/>
      <Note pitch="74" beat="58.75" length="0.2479166666666686" velocity="80"/>
      <Note pitch="72" beat="59.0" length="0.2479166666666686" velocity="80"/>
      <Note pitch="71" beat="59.25" length="0.2479166666666686" velocity="80"/>
      <Note pitch="69" beat="59.5" length="0.2479166666666686" velocity="80"/>
      <Note pitch="71" beat="59.75" length="0.2479166666666686" velocity="80"/>
      <Note pitch="72" beat="60.0" length="0.2479166666666686" velocity="80"/>
      <Note pitch="74" beat="60.25" length="0.2479166666666686" velocity="80"/>
      <Note pitch="76" beat="60.5" length="0.2479166666666686" velocity="80"/>
      <Note pitch="77" beat="60.75" length="0.2479166666666686" velocity="80"/>
      <Note pitch="79" beat="61.0" length="0.2479166666666686" velocity="80"/>
      <Note pitch="81" beat="61.25" length="0.2479166666666686" velocity="80"/>
      <Note pitch="83" beat="61.5" length="0.2479166666666686" velocity="80"/>
      <Note pitch="84" beat="61.75" length="0.2479166666666686" velocity="80"/>
      <Note pitch="72" beat="62.0" length="0.9979166666666686" velocity="80"/>
    </MidiBlock>
  </MidiTrack>
  <MidiTrack id="1082" name="Piano">
    <MidiBlock name="Piano" length="47.99856549583333" id="1099" startBeat="0.0">
      <Note pitch="60" beat="0.0" length="0.2479166666666667" velocity="80"/>
      <Note pitch="48" beat="0.25" length="0.2479166666666667" velocity="80"/>
      <Note pitch="50" beat="0.5" length="0.2479166666666667" velocity="80"/>
      <Note pitch="52" beat="0.75" length="0.2479166666666667" velocity="80"/>
      <Note pitch="53" beat="1.0" length="0.2479166666666666" velocity="80"/>
      <Note pitch="55" beat="1.25" length="0.2479166666666666" velocity="80"/>
      <Note pitch="57" beat="1.5" length="0.2479166666666666" velocity="80"/>
      <Note pitch="59" beat="1.75" length="0.2479166666666666" velocity="80"/>
      <Note pitch="60" beat="2.0" length="0.9979166666666668" velocity="80"/>
      <Note pitch="55" beat="4.0" length="0.9979166666666668" velocity="80"/>
      <Note pitch="43" beat="6.5" length="0.4979166666666668" velocity="80"/>
      <Note pitch="47" beat="7.0" length="0.4979166666666668" velocity="80"/>
      <Note pitch="50" beat="7.5" length="0.4979166666666668" velocity="80"/>
      <Note pitch="55" beat="8.0" length="0.2479166666666668" velocity="80"/>
      <Note pitch="43" beat="8.25" length="0.2479166666666668" velocity="80"/>
      <Note pitch="45" beat="8.5" length="0.2479166666666668" velocity="80"/>
      <Note pitch="47" beat="8.75" length="0.2479166666666668" velocity="80"/>
      <Note pitch="48" beat="9.0" length="0.2479166666666668" velocity="80"/>
      <Note pitch="50" beat="9.25" length="0.2479166666666668" velocity="80"/>
      <Note pitch="52" beat="9.5" length="0.2479166666666668" velocity="80"/>
      <Note pitch="54" beat="9.75" length="0.2479166666666668" velocity="80"/>
      <Note pitch="55" beat="10.0" length="0.9979166666666668" velocity="80"/>
      <Note pitch="48" beat="12.0" length="0.9979166666666668" velocity="80"/>
      <Note pitch="48" beat="14.5" length="0.4979166666666668" velocity="80"/>
      <Note pitch="52" beat="15.0" length="0.4979166666666668" velocity="80"/>
      <Note pitch="55" beat="15.5" length="0.4979166666666668" velocity="80"/>
      <Note pitch="48" beat="16.0" length="1.997916666666665" velocity="80"/>
      <Note pitch="50" beat="16.0" length="1.997916666666665" velocity="80"/>
      <Note pitch="54" beat="16.0" length="1.997916666666665" velocity="80"/>
      <Note pitch="57" beat="16.0" length="1.997916666666665" velocity="80"/>
      <Note pitch="48" beat="18.5" length="0.497916666666665" velocity="80"/>
      <Note pitch="50" beat="18.5" length="0.497916666666665" velocity="80"/>
      <Note pitch="54" beat="18.5" length="0.497916666666665" velocity="80"/>
      <Note pitch="57" beat="18.5" length="0.497916666666665" velocity="80"/>
      <Note pitch="48" beat="19.0" length="0.497916666666665" velocity="80"/>
      <Note pitch="50" beat="19.0" length="0.497916666666665" velocity="80"/>
      <Note pitch="54" beat="19.0" length="0.497916666666665" velocity="80"/>
      <Note pitch="57" beat="19.0" length="0.497916666666665" velocity="80"/>
      <Note pitch="48" beat="19.5" length="0.497916666666665" velocity="80"/>
      <Note pitch="50" beat="19.5" length="0.497916666666665" velocity="80"/>
      <Note pitch="54" beat="19.5" length="0.497916666666665" velocity="80"/>
      <Note pitch="57" beat="19.5" length="0.497916666666665" velocity="80"/>
      <Note pitch="47" beat="20.0" length="1.997916666666665" velocity="80"/>
      <Note pitch="50" beat="20.0" length="1.997916666666665" velocity="80"/>
      <Note pitch="55" beat="20.0" length="1.997916666666665" velocity="80"/>
      <Note pitch="47" beat="22.5" length="0.497916666666665" velocity="80"/>
      <Note pitch="50" beat="22.5" length="0.497916666666665" velocity="80"/>
      <Note pitch="55" beat="22.5" length="0.497916666666665" velocity="80"/>
      <Note pitch="47" beat="23.0" length="0.497916666666665" velocity="80"/>
      <Note pitch="50" beat="23.0" length="0.497916666666665" velocity="80"/>
      <Note pitch="55" beat="23.0" length="0.497916666666665" velocity="80"/>
      <Note pitch="47" beat="23.5" length="0.497916666666665" velocity="80"/>
      <Note pitch="50" beat="23.5" length="0.497916666666665" velocity="80"/>
      <Note pitch="55" beat="23.5" length="0.497916666666665" velocity="80"/>
      <Note pitch="48" beat="24.0" length="1.997916666666665" velocity="80"/>
      <Note pitch="52" beat="24.0" length="1.997916666666665" velocity="80"/>
      <Note pitch="57" beat="24.0" length="1.997916666666665" velocity="80"/>
      <Note pitch="50" beat="26.0" length="1.997916666666665" velocity="80"/>
      <Note pitch="57" beat="26.0" length="1.997916666666665" velocity="80"/>
      <Note pitch="60" beat="26.0" length="1.997916666666665" velocity="80"/>
      <Note pitch="55" beat="28.0" length="1.997916666666665" velocity="80"/>
      <Note pitch="59" beat="28.0" length="1.997916666666665" velocity="80"/>
      <Note pitch="55" beat="30.5" length="0.497916666666665" velocity="80"/>
      <Note pitch="53" beat="31.0" length="0.497916666666665" velocity="80"/>
      <Note pitch="50" beat="31.5" length="0.497916666666665" velocity="80"/>
      <Note pitch="49" beat="32.0" length="1.997916666666669" velocity="80"/>
      <Note pitch="52" beat="32.0" length="1.997916666666669" velocity="80"/>
      <Note pitch="57" beat="32.0" length="1.997916666666669" velocity="80"/>
      <Note pitch="49" beat="34.5" length="0.4979166666666686" velocity="80"/>
      <Note pitch="52" beat="34.5" length="0.4979166666666686" velocity="80"/>
      <Note pitch="55" beat="34.5" length="0.4979166666666686" velocity="80"/>
      <Note pitch="57" beat="34.5" length="0.4979166666666686" velocity="80"/>
      <Note pitch="49" beat="35.0" length="0.4979166666666686" velocity="80"/>
      <Note pitch="52" beat="35.0" length="0.4979166666666686" velocity="80"/>
      <Note pitch="55" beat="35.0" length="0.4979166666666686" velocity="80"/>
      <Note pitch="57" beat="35.0" length="0.4979166666666686" velocity="80"/>
      <Note pitch="49" beat="35.5" length="0.4979166666666686" velocity="80"/>
      <Note pitch="52" beat="35.5" length="0.4979166666666686" velocity="80"/>
      <Note pitch="55" beat="35.5" length="0.4979166666666686" velocity="80"/>
      <Note pitch="57" beat="35.5" length="0.4979166666666686" velocity="80"/>
      <Note pitch="50" beat="36.0" length="1.997916666666669" velocity="80"/>
      <Note pitch="53" beat="36.0" length="1.997916666666669" velocity="80"/>
      <Note pitch="57" beat="36.0" length="1.997916666666669" velocity="80"/>
      <Note pitch="50" beat="38.5" length="0.4979166666666686" velocity="80"/>
      <Note pitch="53" beat="39.0" length="0.4979166666666686" velocity="80"/>
      <Note pitch="50" beat="39.5" length="0.4979166666666686" velocity="80"/>
      <Note pitch="47" beat="40.0" length="1.997916666666669" velocity="80"/>
      <Note pitch="50" beat="40.0" length="1.997916666666669" velocity="80"/>
      <Note pitch="53" beat="40.0" length="1.997916666666669" velocity="80"/>
      <Note pitch="55" beat="40.0" length="1.997916666666669" velocity="80"/>
      <Note pitch="47" beat="42.5" length="0.4979166666666686" velocity="80"/>
      <Note pitch="50" beat="42.5" length="0.4979166666666686" velocity="80"/>
      <Note pitch="53" beat="42.5" length="0.4979166666666686" velocity="80"/>
      <Note pitch="55" beat="42.5" length="0.4979166666666686" velocity="80"/>
      <Note pitch="47" beat="43.0" length="0.4979166666666686" velocity="80"/>
      <Note pitch="50" beat="43.0" length="0.4979166666666686" velocity="80"/>
      <Note pitch="53" beat="43.0" length="0.4979166666666686" velocity="80"/>
      <Note pitch="55" beat="43.0" length="0.4979166666666686" velocity="80"/>
      <Note pitch="47" beat="43.5" length="0.4979166666666686" velocity="80"/>
      <Note pitch="50" beat="43.5" length="0.4979166666666686" velocity="80"/>
      <Note pitch="53" beat="43.5" length="0.4979166666666686" velocity="80"/>
      <Note pitch="55" beat="43.5" length="0.4979166666666686" velocity="80"/>
      <Note pitch="48" beat="44.0" length="0.9979166666666686" velocity="80"/>
      <Note pitch="52" beat="44.0" length="0.9979166666666686" velocity="80"/>
      <Note pitch="55" beat="44.0" length="0.9979166666666686" velocity="80"/>
      <Note pitch="48" beat="46.5" length="0.4979166666666686" velocity="80"/>
      <Note pitch="52" beat="47.0" length="0.4979166666666686" velocity="80"/>
      <Note pitch="55" beat="47.5" length="0.4979166666666686" velocity="80"/>
      <Note pitch="60" beat="48.0" length="0.2479166666666686" velocity="80"/>
      <Note pitch="48" beat="48.25" length="0.2479166666666686" velocity="80"/>
      <Note pitch="50" beat="48.5" length="0.2479166666666686" velocity="80"/>
      <Note pitch="52" beat="48.75" length="0.2479166666666686" velocity="80"/>
      <Note pitch="53" beat="49.0" length="0.2479166666666686" velocity="80"/>
      <Note pitch="55" beat="49.25" length="0.2479166666666686" velocity="80"/>
      <Note pitch="57" beat="49.5" length="0.2479166666666686" velocity="80"/>
      <Note pitch="59" beat="49.75" length="0.2479166666666686" velocity="80"/>
      <Note pitch="60" beat="50.0" length="0.9979166666666686" velocity="80"/>
      <Note pitch="57" beat="52.0" length="0.2479166666666686" velocity="80"/>
      <Note pitch="53" beat="52.25" length="0.2479166666666686" velocity="80"/>
      <Note pitch="55" beat="52.5" length="0.2479166666666686" velocity="80"/>
      <Note pitch="57" beat="52.75" length="0.2479166666666686" velocity="80"/>
      <Note pitch="58" beat="53.0" length="0.2479166666666686" velocity="80"/>
      <Note pitch="60" beat="53.25" length="0.2479166666666686" velocity="80"/>
      <Note pitch="62" beat="53.5" length="0.2479166666666686" velocity="80"/>
      <Note pitch="64" beat="53.75" length="0.2479166666666686" velocity="80"/>
      <Note pitch="65" beat="54.0" length="0.9979166666666686" velocity="80"/>
      <Note pitch="55" beat="56.0" length="1.997916666666669" velocity="80"/>
      <Note pitch="60" beat="56.0" length="1.997916666666669" velocity="80"/>
      <Note pitch="64" beat="56.0" length="1.997916666666669" velocity="80"/>
      <Note pitch="55" beat="58.0" length="1.997916666666669" velocity="80"/>
      <Note pitch="62" beat="58.0" length="1.997916666666669" velocity="80"/>
      <Note pitch="65" beat="58.0" length="1.997916666666669" velocity="80"/>
      <Note pitch="60" beat="60.0" length="1.997916666666669" velocity="80"/>
      <Note pitch="64" beat="60.0" length="1.997916666666669" velocity="80"/>
      <Note pitch="48" beat="63.0" length="0.9979166666666686" velocity="80"/>
    </MidiBlock>
  </MidiTrack>
  <AudioTrack id="1037"/>
</Music>
